pipeline_live/__init__.py
pipeline_live/_version.py
pipeline_live/engine.py
pipeline_live/data/__init__.py
pipeline_live/data/alpaca/__init__.py
pipeline_live/data/alpaca/factors.py
pipeline_live/data/alpaca/pricing.py
pipeline_live/data/alpaca/pricing_loader.py
pipeline_live/data/iex/__init__.py
pipeline_live/data/iex/classifiers.py
pipeline_live/data/iex/factors.py
pipeline_live/data/iex/fundamentals.py
pipeline_live/data/iex/fundamentals_loader.py
pipeline_live/data/iex/pricing.py
pipeline_live/data/iex/pricing_loader.py
pipeline_live/data/sources/__init__.py
pipeline_live/data/sources/alpaca.py
pipeline_live/data/sources/iex.py
pipeline_live/data/sources/util.py
tests/__init__.py
tests/conftest.py
tests/test_alpaca.py
tests/test_engine.py
tests/test_factors.py
tests/test_iex.py
tests/test_sources.py
tests/datamock/__init__.py
tests/datamock/mock_iex.py
tests/datamock/mock_tradeapi.py
pipeline_live-0.2.0.dist-info/LICENSE
pipeline_live-0.2.0.dist-info/METADATA
pipeline_live-0.2.0.dist-info/WHEEL
pipeline_live-0.2.0.dist-info/top_level.txt
pipeline_live-0.2.0.dist-info/RECORD
