Metadata-Version: 2.1
Name: pipeline-live
Version: 0.2.0
Summary: Zipline Pipeline extension for live trade
Home-page: https://github.com/alpacahq/pipeline_live
Author: Alpaca
Author-email: oss@alpaca.markets
License: UNKNOWN
Keywords: financial,zipline,pipeline,stock,screening,api,trade
Platform: UNKNOWN
License-File: LICENSE
Requires-Dist: pandas (==0.22.0)
Requires-Dist: numpy (==1.19.4)
Requires-Dist: scipy (<=1.6.0)
Requires-Dist: pandas-datareader (<=0.8.1)
Requires-Dist: lxml (>=4.6.2)
Requires-Dist: alpaca-trade-api (==1.5.0)
Requires-Dist: iexfinance (<0.5.0,>=0.4.1)
Requires-Dist: zipline (==1.3.0)
